velin/__init__.py
velin/__main__.py
velin/examples_section_utils.py
velin/ref.py
velin-0.0.11.dist-info/entry_points.txt
velin-0.0.11.dist-info/LICENSE
velin-0.0.11.dist-info/WHEEL
velin-0.0.11.dist-info/METADATA
velin-0.0.11.dist-info/RECORD
