Metadata-Version: 2.1
Name: velin
Version: 0.0.11
Summary: French for Vellum
Home-page: https://github.com/Carreau/minirst
License: UNKNOWN
Author: Matthias Bussonnier
Author-email: bussonniermatthias@gmail.com
Requires-Python: >=3.8
Classifier: License :: OSI Approved :: MIT License
Requires-Dist: numpydoc
Requires-Dist: pygments
Requires-Dist: black
Requires-Dist: there
